{"quoteType": "MUTUALFUND", "symbol": "ARG", "language": "en-US", "region": "US", "typeDisp": "Fund", "quoteSourceName": "Delayed Quote", "triggerable": false, "customPriceAlertConfidence": "NONE", "shortName": "386692", "hasPrePostMarketData": false, "firstTradeDateMilliseconds": 1558963800000, "priceHint": 2, "marketState": "POST", "fullExchangeName": "YHD", "sourceInterval": 15, "exchangeDataDelayedBy": 0, "tradeable": false, "cryptoTradeable": false, "regularMarketTime": 1561759658, "exchange": "YHD", "exchangeTimezoneName": "America/New_York", "exchangeTimezoneShortName": "EDT", "gmtOffSetMilliseconds": -14400000, "market": "us_market", "esgPopulated": false, "corporateActions": [], "trailingPegRatio": null}