{"address1": "345 Park Avenue", "city": "New York", "state": "NY", "zip": "10154", "country": "United States", "phone": "(212) 583-5000", "fax": "(212) 583-5749", "website": "https://www.blackstone.com", "industry": "Asset Management", "industryKey": "asset-management", "industryDisp": "Asset Management", "sector": "Financial Services", "sectorKey": "financial-services", "sectorDisp": "Financial Services", "longBusinessSummary": "Blackstone Inc. is an alternative asset management firm specializing in private equity, real estate, hedge fund solutions, credit, secondary funds of funds, public debt and equity and multi-asset class strategies. The firm typically invests in early-stage, seed, middle market, mature, late venture, growth capital, emerging growth and later stage companies. It also provide capital markets services. The real estate segment specializes in opportunistic, core+ investments as well as debt investment opportunities collateralized by commercial real estate, and stabilized income-oriented commercial real estate across North America, Europe and Asia. The firm's corporate private equity business pursues transactions throughout the world across a variety of transaction types, including large buyouts, recapitalization, special situations, distressed mortgage loans, mid-cap buyouts, buy and build platforms, which involves multiple acquisitions behind a single management team and platform, and growth equity/development projects involving significant majority stakes in portfolio companies and minority investments in operating companies, shipping, real estate, corporate or consumer loans, and alternative energy greenfield development projects in energy and power, property, dislocated markets, shipping opportunities, financial institution breakups, re-insurance, and improving freight mobility, financial services, cargo, data processing, oil & gas production, oil & gas refining, oil & gas storage, building products, home entertainment, B2B, consumer electronics, home supply store, lodging, commercial services & supplies, metal & mineral mining machinery, coal, hazardous waste collection, solid waste collection, waste water treatment, renewable electricity, equity REITs, power generation by nuclear & fossil fuels, personal loan services, chemcials, other specialty retail, biotech, pharmaceuticals, metal, aerospace, healthcare, cable, entertainment services, infrastructure services, transportation infrastructure, exhaust, life sciences, alternative carriers, infrastructure, system software, manufacturing services, enterprise tech and consumer, enterprise software & application, as well as consumer technologies. The firm considers investment in Asia and Latin America. It seeks to invest between $0.25 million and $900 million per transaction. It invests in companies with enterprise value between $500 million and $5000 million. It has a three year investment period. The firm prefers to take majority and minority stakes. Its hedge fund business manages a broad range of commingled and customized fund solutions and its credit business focuses on loans, and securities of non-investment grade companies spread across the capital structure including senior debt, subordinated debt, preferred stock and common equity. Blackstone Inc. was founded in 1985 and is headquartered in New York, New York with additional offices across Asia, Europe, North America and Central America.", "fullTimeEmployees": 4895, "companyOfficers": [{"maxAge": 1, "name": "Mr. Stephen Allen Schwarzman B.A., M.B.A.", "age": 77, "title": "Chairman, CEO & Co-Founder", "yearBorn": 1947, "fiscalYear": 2024, "totalPay": 84027074, "exercisedValue": 0, "unexercisedValue": 0}, {"maxAge": 1, "name": "Mr. Jonathan D. Gray CIMA", "age": 55, "title": "General Partner, President, COO & Director", "yearBorn": 1969, "fiscalYear": 2024, "totalPay": 44491580, "exercisedValue": 0, "unexercisedValue": 0}, {"maxAge": 1, "name": "Mr. Michael S. Chae J.D.", "age": 56, "title": "CFO & Vice Chairman", "yearBorn": 1968, "fiscalYear": 2024, "totalPay": 5574642, "exercisedValue": 0, "unexercisedValue": 0}, {"maxAge": 1, "name": "Mr. Vikrant  Sawhney J.D.", "title": "Chief Administrative Officer & Global Head of Institutional Client Solutions", "fiscalYear": 2024, "totalPay": 8921538, "exercisedValue": 0, "unexercisedValue": 0}, {"maxAge": 1, "name": "Mr. John Gary Finley", "age": 67, "title": "Chief Legal Officer", "yearBorn": 1957, "fiscalYear": 2024, "totalPay": 5776059, "exercisedValue": 0, "unexercisedValue": 0}, {"maxAge": 1, "name": "Mr. Joseph Patrick Baratta", "age": 53, "title": "Global Head of Private Equity Strategies & Director", "yearBorn": 1971, "fiscalYear": 2024, "exercisedValue": 0, "unexercisedValue": 0}, {"maxAge": 1, "name": "Mr. William J. Stein", "age": 62, "title": "Senior Managing Director of Real Estate- New York", "yearBorn": 1962, "fiscalYear": 2024, "exercisedValue": 0, "unexercisedValue": 0}, {"maxAge": 1, "name": "Mr. Robert Christopher Heady", "title": "Senior MD - Hong Kong, Head of Asia Real Estate & Chairman of Asia Pacific", "fiscalYear": 2024, "totalPay": 4932575, "exercisedValue": 0, "unexercisedValue": 0}, {"maxAge": 1, "name": "Mr. Michael B. Nash", "age": 63, "title": "Senior MD of Real Estate & Co-Founder and Chairman of Blackstone Real Estate Debt Strategies", "yearBorn": 1961, "fiscalYear": 2024, "exercisedValue": 0, "unexercisedValue": 0}, {"maxAge": 1, "name": "Mr. Mustafa Mohsin Siddiqui", "title": "Former Senior MD of BXMA - New York & Co-Head of Strategic Capital Group", "fiscalYear": 2024, "exercisedValue": 0, "unexercisedValue": 0}], "auditRisk": 9, "boardRisk": 10, "compensationRisk": 9, "shareHolderRightsRisk": 10, "overallRisk": 10, "governanceEpochDate": 1746057600, "compensationAsOfEpochDate": 1735603200, "executiveTeam": [], "maxAge": 86400, "priceHint": 2, "previousClose": 144.2, "open": 142.02, "dayLow": 137.19, "dayHigh": 142.8203, "regularMarketPreviousClose": 144.2, "regularMarketOpen": 142.02, "regularMarketDayLow": 137.19, "regularMarketDayHigh": 142.8203, "dividendRate": 4.05, "dividendYield": 2.81, "exDividendDate": 1745798400, "payoutRatio": 1.197, "fiveYearAvgDividendYield": 3.39, "beta": 1.662, "trailingPE": 41.590908, "forwardPE": 23.542025, "volume": 3046693, "regularMarketVolume": 3046759, "averageVolume": 5313722, "averageVolume10days": 3832430, "averageDailyVolume10Day": 3832430, "bid": 137.27, "ask": 137.36, "bidSize": 11, "askSize": 10, "marketCap": 166515818496, "fiftyTwoWeekLow": 115.66, "fiftyTwoWeekHigh": 200.96, "priceToSalesTrailing12Months": 13.458287, "fiftyDayAverage": 138.0402, "twoHundredDayAverage": 157.21175, "trailingAnnualDividendRate": 4.05, "trailingAnnualDividendYield": 0.028085994, "currency": "USD", "tradeable": false, "enterpriseValue": 135318331392, "profitMargins": 0.20561, "floatShares": 733436149, "sharesOutstanding": 729648000, "sharesShort": 12380879, "sharesShortPriorMonth": 9994217, "sharesShortPreviousMonthDate": 1743379200, "dateShortInterest": 1745971200, "sharesPercentSharesOut": 0.0162, "heldPercentInsiders": 0.0099, "heldPercentInstitutions": 0.71269, "shortRatio": 1.75, "shortPercentOfFloat": 0.017, "impliedSharesOutstanding": 1213229952, "bookValue": 10.32, "priceToBook": 13.299419, "lastFiscalYearEnd": 1735603200, "nextFiscalYearEnd": 1767139200, "mostRecentQuarter": 1743379200, "earningsQuarterlyGrowth": -0.274, "netIncomeToCommon": 2543973888, "trailingEps": 3.3, "forwardEps": 5.83, "enterpriseToRevenue": 10.937, "52WeekChange": 0.13830125, "SandP52WeekChange": 0.11936104, "lastDividendValue": 0.93, "lastDividendDate": 1745798400, "quoteType": "EQUITY", "currentPrice": 137.25, "targetHighPrice": 196.0, "targetLowPrice": 109.0, "targetMeanPrice": 147.11047, "targetMedianPrice": 144.0, "recommendationMean": 2.26087, "recommendationKey": "buy", "numberOfAnalystOpinions": 21, "totalCash": 2562064896, "totalCashPerShare": 3.314, "totalDebt": 14521400320, "quickRatio": 0.821, "currentRatio": 0.941, "totalRevenue": 12372734976, "debtToEquity": 73.101, "revenuePerShare": 16.079, "returnOnAssets": 0.11889, "returnOnEquity": 0.26345, "grossProfits": 12372734976, "operatingCashflow": 3651034112, "earningsGrowth": -0.282, "revenueGrowth": -0.082, "grossMargins": 1.0, "ebitdaMargins": 0.0, "operatingMargins": 0.45259, "financialCurrency": "USD", "symbol": "BX", "language": "en-US", "region": "US", "typeDisp": "Equity", "quoteSourceName": "Nasdaq Real Time Price", "triggerable": true, "customPriceAlertConfidence": "HIGH", "marketState": "REGULAR", "corporateActions": [], "regularMarketTime": 1747855527, "hasPrePostMarketData": true, "firstTradeDateMilliseconds": 1182519000000, "regularMarketChange": -6.949997, "regularMarketDayRange": "137.19 - 142.8203", "fullExchangeName": "NYSE", "averageDailyVolume3Month": 5313722, "fiftyTwoWeekLowChange": 21.589996, "fiftyTwoWeekLowChangePercent": 0.18666779, "fiftyTwoWeekRange": "115.66 - 200.96", "fiftyTwoWeekHighChange": -63.710007, "fiftyTwoWeekHighChangePercent": -0.31702828, "fiftyTwoWeekChangePercent": 13.830126, "dividendDate": 1746403200, "earningsTimestamp": 1744893000, "earningsTimestampStart": 1752669000, "earningsTimestampEnd": 1753101000, "earningsCallTimestampStart": 1744894800, "earningsCallTimestampEnd": 1744894800, "isEarningsDateEstimate": true, "epsTrailingTwelveMonths": 3.3, "epsForward": 5.83, "epsCurrentYear": 4.91365, "priceEpsCurrentYear": 27.932392, "fiftyDayAverageChange": -0.7902069, "fiftyDayAverageChangePercent": -0.005724469, "twoHundredDayAverageChange": -19.961746, "twoHundredDayAverageChangePercent": -0.12697363, "sourceInterval": 15, "exchangeDataDelayedBy": 0, "prevName": "The Blackstone Group Inc.", "nameChangeDate": "2025-05-21", "averageAnalystRating": "2.3 - Buy", "cryptoTradeable": false, "regularMarketChangePercent": -4.819693, "regularMarketPrice": 137.25, "exchange": "NYQ", "messageBoardId": "finmb_671980", "exchangeTimezoneName": "America/New_York", "exchangeTimezoneShortName": "EDT", "gmtOffSetMilliseconds": -14400000, "market": "us_market", "esgPopulated": false, "shortName": "Blackstone Inc.", "longName": "Blackstone Inc.", "displayName": "Blackstone", "trailingPegRatio": 2.1144}